Levenshtein_search.cp38-win_amd64.pyd
dedupe_Levenshtein_search-1.4.5.dist-info/LICENSE
dedupe_Levenshtein_search-1.4.5.dist-info/METADATA
dedupe_Levenshtein_search-1.4.5.dist-info/WHEEL
dedupe_Levenshtein_search-1.4.5.dist-info/top_level.txt
dedupe_Levenshtein_search-1.4.5.dist-info/RECORD
