Metadata-Version: 2.1
Name: dedupe-Levenshtein-search
Version: 1.4.5
Summary: Search through documents for approximately matching strings. A fork of Matt Anderson's library for MIT licensing
Home-page: https://github.com/dedupeio/Levenshtein_search
Author: Matt Anderson
Maintainer: Forest Gregg
Classifier: Topic :: Software Development :: Libraries :: Python Modules
Classifier: Topic :: Scientific/Engineering
Classifier: Topic :: Scientific/Engineering :: Information Analysis
License-File: LICENSE
